pixano/__init__.py
pixano/__version__.py
pixano/app/README.md
pixano/app/__init__.py
pixano/app/display.py
pixano/app/main.py
pixano/app/serve.py
pixano/app/settings.py
pixano/app/dist/favicon.ico
pixano/app/dist/index.html
pixano/app/dist/robots.txt
pixano/app/dist/_app/env.js
pixano/app/dist/_app/version.json
pixano/app/dist/_app/immutable/assets/0.tlEX1B1x.css
pixano/app/dist/_app/immutable/assets/4.XIn10Jg4.css
pixano/app/dist/_app/immutable/assets/5.suJzFF5v.css
pixano/app/dist/_app/immutable/assets/_layout.B5OrUZnr.css
pixano/app/dist/_app/immutable/assets/_page.BXvTtRs3.css
pixano/app/dist/_app/immutable/assets/_page.XIn10Jg4.css
pixano/app/dist/_app/immutable/assets/completed-question.B-dh-nyt.png
pixano/app/dist/_app/immutable/assets/favicon.OuiISzV3.ico
pixano/app/dist/_app/immutable/assets/pixano.NAI_8qFW.png
pixano/app/dist/_app/immutable/assets/pixano_white.BVKPSmmP.png
pixano/app/dist/_app/immutable/chunks/8RsWtykp.js
pixano/app/dist/_app/immutable/chunks/B81L-OfO.js
pixano/app/dist/_app/immutable/chunks/B9u33kEZ.js
pixano/app/dist/_app/immutable/chunks/BQqikIAS.js
pixano/app/dist/_app/immutable/chunks/BU7plhYt.js
pixano/app/dist/_app/immutable/chunks/BeJwflgO.js
pixano/app/dist/_app/immutable/chunks/C13LPUBZ.js
pixano/app/dist/_app/immutable/chunks/CPVtFGAp.js
pixano/app/dist/_app/immutable/chunks/CXBIDK6p.js
pixano/app/dist/_app/immutable/chunks/CXVjQPh2.js
pixano/app/dist/_app/immutable/chunks/CoGE4j-f.js
pixano/app/dist/_app/immutable/chunks/CyVEvHZA.js
pixano/app/dist/_app/immutable/chunks/DPkO8WLB.js
pixano/app/dist/_app/immutable/chunks/_l3qLYZn.js
pixano/app/dist/_app/immutable/chunks/fM4OTL4z.js
pixano/app/dist/_app/immutable/entry/app.BlMuLlKR.js
pixano/app/dist/_app/immutable/entry/start.pCCk6Kzc.js
pixano/app/dist/_app/immutable/nodes/0.CfUeJTUe.js
pixano/app/dist/_app/immutable/nodes/1.B6qFyRVf.js
pixano/app/dist/_app/immutable/nodes/2.BeAz2TNE.js
pixano/app/dist/_app/immutable/nodes/3.BMgsyXGa.js
pixano-0.6.12.dist-info/METADATA
pixano-0.6.12.dist-info/WHEEL
pixano-0.6.12.dist-info/entry_points.txt
pixano-0.6.12.dist-info/licenses/LICENSE
pixano-0.6.12.dist-info/RECORD
