Metadata-Version: 2.4
Name: pixano
Version: 0.6.12
Summary: Data-centric AI building blocks for computer vision applications
Project-URL: Documentation, https://github.com/pixano/pixano#readme
Project-URL: Issues, https://github.com/pixano/pixano/issues
Project-URL: Source, https://github.com/pixano/pixano
Author-email: Pixano Developers <pixano@cea.fr>
License-Expression: CECILL-C
License-File: LICENSE
Keywords: computer vision,data annotation,data visualization,deep learning,machine learning
Classifier: Development Status :: 4 - Beta
Classifier: License :: CeCILL-C Free Software License Agreement (CECILL-C)
Classifier: Programming Language :: Python :: 3.10
Classifier: Programming Language :: Python :: 3.11
Classifier: Programming Language :: Python :: 3.12
Classifier: Programming Language :: Python :: 3.13
Requires-Python: <3.14,>=3.10
Requires-Dist: duckdb<2.0.0,>=1.0.0
Requires-Dist: fastapi<1.0.0,>=0.103.0
Requires-Dist: httpx<1.0.0,>=0.25.0
Requires-Dist: importlib-resources<6.0.0,>=5.12.0
Requires-Dist: ipywidgets<9.0.0,>=8.0.0
Requires-Dist: jinja2<4.0.0,>=3.1.2
Requires-Dist: lancedb<0.18.0,>=0.17.0
Requires-Dist: numpy<2.0.0,>=1.18.0
Requires-Dist: opencv-python<5.0.0,>=4.7.0
Requires-Dist: pandas<3.0.0,>=1.5.0
Requires-Dist: pillow<11.0.0,>=9.4.0
Requires-Dist: pixano-inference~=0.5.6
Requires-Dist: polars<2.0.0,>1.7.0
Requires-Dist: pycocotools<3.0.0,>=2.0.0
Requires-Dist: pydantic-settings<3.0.0,>=2.0.0
Requires-Dist: pydantic<3.0.0,>=2.9.0
Requires-Dist: s3path<1.0.0,>=0.5.0
Requires-Dist: setuptools<76.0.0,>=65.6.0
Requires-Dist: shortuuid<2.0.0,>=1.0.0
Requires-Dist: tqdm<5.0.0,>=4.64.0
Requires-Dist: uvicorn<1.0.0,>=0.20.0
Provides-Extra: docs
Requires-Dist: mike<3.0.0,>=2.1.0; extra == 'docs'
Requires-Dist: mkdocs-gen-files>=0.5.0; extra == 'docs'
Requires-Dist: mkdocs-literate-nav>=0.6.0; extra == 'docs'
Requires-Dist: mkdocs-material<10.0.0,>=9.5.0; extra == 'docs'
Requires-Dist: mkdocs-redirects>=1.2.1; extra == 'docs'
Requires-Dist: mkdocs<2.0.0,>=1.6.0; extra == 'docs'
Requires-Dist: mkdocstrings-python>=1.7.0; extra == 'docs'
Provides-Extra: test
Requires-Dist: ffmpeg-python<0.3.0,>=0.2.0; extra == 'test'
Requires-Dist: mediapy; extra == 'test'
Requires-Dist: pytest; extra == 'test'
Requires-Dist: pytest-asyncio; extra == 'test'
Requires-Dist: pytest-cov; extra == 'test'
Requires-Dist: pytest-mock; extra == 'test'
